euler2_gl-1.0.0.data/purelib/euler/__init__.py
euler2_gl-1.0.0.data/purelib/euler/python/__init__.py
euler2_gl-1.0.0.data/purelib/euler/python/hash_test.py
euler2_gl-1.0.0.data/purelib/euler/python/libeuler_core.so
euler2_gl-1.0.0.data/purelib/euler/python/start_service.py
euler2_gl-1.0.0.data/purelib/euler/tools/__init__.py
euler2_gl-1.0.0.data/purelib/euler/tools/edge.py
euler2_gl-1.0.0.data/purelib/euler/tools/generate_euler_data.py
euler2_gl-1.0.0.data/purelib/euler/tools/graph_meta.py
euler2_gl-1.0.0.data/purelib/euler/tools/json2meta.py
euler2_gl-1.0.0.data/purelib/euler/tools/json2partdat.py
euler2_gl-1.0.0.data/purelib/euler/tools/json2partindex.py
euler2_gl-1.0.0.data/purelib/euler/tools/libcommon.so
euler2_gl-1.0.0.data/purelib/euler/tools/libeuler_util.so
euler2_gl-1.0.0.data/purelib/euler/tools/node.py
euler2_gl-1.0.0.data/purelib/euler/tools/util.py
euler2_gl-1.0.0.data/purelib/euler_estimator/__init__.py
euler2_gl-1.0.0.data/purelib/euler_estimator/python/__init__.py
euler2_gl-1.0.0.data/purelib/euler_estimator/python/base_estimator.py
euler2_gl-1.0.0.data/purelib/euler_estimator/python/edge_estimator.py
euler2_gl-1.0.0.data/purelib/euler_estimator/python/gae_estimator.py
euler2_gl-1.0.0.data/purelib/euler_estimator/python/graph_estimator.py
euler2_gl-1.0.0.data/purelib/euler_estimator/python/node_estimator.py
euler2_gl-1.0.0.data/purelib/euler_estimator/python/sample_estimator.py
euler2_gl-1.0.0.data/purelib/tf_euler/__init__.py
euler2_gl-1.0.0.data/purelib/tf_euler/python/__init__.py
euler2_gl-1.0.0.data/purelib/tf_euler/python/convolution/__init__.py
euler2_gl-1.0.0.data/purelib/tf_euler/python/convolution/agnn_conv.py
euler2_gl-1.0.0.data/purelib/tf_euler/python/convolution/appnp_conv.py
euler2_gl-1.0.0.data/purelib/tf_euler/python/convolution/arma_conv.py
euler2_gl-1.0.0.data/purelib/tf_euler/python/convolution/conv.py
euler2_gl-1.0.0.data/purelib/tf_euler/python/convolution/conv_test.py
euler2_gl-1.0.0.dist-info/DESCRIPTION.rst
euler2_gl-1.0.0.dist-info/METADATA
euler2_gl-1.0.0.dist-info/RECORD
euler2_gl-1.0.0.dist-info/WHEEL
euler2_gl-1.0.0.dist-info/metadata.json
euler2_gl-1.0.0.dist-info/top_level.txt
