Metadata-Version: 2.0
Name: euler2-gl
Version: 1.0.0
Summary: A toolset for network representation learning.
Home-page: https://github.com/alibaba/euler
Author: Alibaba Group Holding Limited
Author-email: euler-opensource@list.alibaba-inc.com
License: Apache License 2.0
Platform: UNKNOWN
Requires-Dist: tensorflow (==1.12.0)
Requires-Dist: tqdm
Requires-Dist: scipy (==1.1.0)
Requires-Dist: networkx (==1.11)
Requires-Dist: scikit-learn (==0.19.1)
